fxsdk/__init__.py
fxsdk/coin.py
fxsdk/dec.py
fxsdk/websockets.py
fxsdk/client/__init__.py
fxsdk/client/crosschain.py
fxsdk/client/grpc.py
fxsdk/client/http.py
fxsdk/client/marginx.py
fxsdk/client/scan.py
fxsdk/client/websockets.py
fxsdk/msg/__init__.py
fxsdk/msg/event.py
fxsdk/msg/marginx.py
fxsdk/wallet/__init__.py
fxsdk/wallet/address.py
fxsdk/wallet/builder.py
fxsdk/wallet/key.py
fxsdk/x/__init__.py
fxsdk/x/cosmos/__init__.py
fxsdk/x/cosmos/app/__init__.py
fxsdk/x/cosmos/app/module/__init__.py
fxsdk/x/cosmos/app/module/v1alpha1/__init__.py
fxsdk/x/cosmos/app/module/v1alpha1/module_pb2.py
fxsdk/x/cosmos/app/module/v1alpha1/module_pb2_grpc.py
fxsdk/x/cosmos/app/v1alpha1/__init__.py
fxsdk/x/cosmos/app/v1alpha1/config_pb2.py
fxsdk/x/cosmos/app/v1alpha1/config_pb2_grpc.py
fxsdk/x/cosmos/app/v1alpha1/module_pb2.py
fxsdk/x/cosmos/app/v1alpha1/module_pb2_grpc.py
fxsdk/x/cosmos/app/v1alpha1/query_pb2.py
fxsdk/x/cosmos/app/v1alpha1/query_pb2_grpc.py
fxsdk/x/cosmos/auth/__init__.py
fxsdk/x/cosmos/auth/v1beta1/__init__.py
fxsdk/x/cosmos/auth/v1beta1/auth_pb2.py
fxsdk/x/cosmos/auth/v1beta1/auth_pb2_grpc.py
fxsdk/x/cosmos/auth/v1beta1/genesis_pb2.py
fxsdk/x/cosmos/auth/v1beta1/genesis_pb2_grpc.py
fxsdk/x/cosmos/auth/v1beta1/query_pb2.py
fxsdk/x/cosmos/auth/v1beta1/query_pb2_grpc.py
fxsdk/x/cosmos/authz/__init__.py
fxsdk/x/cosmos/authz/v1beta1/__init__.py
fxsdk/x/cosmos/authz/v1beta1/authz_pb2.py
fxsdk/x/cosmos/authz/v1beta1/authz_pb2_grpc.py
fxsdk/x/cosmos/authz/v1beta1/event_pb2.py
fxsdk/x/cosmos/authz/v1beta1/event_pb2_grpc.py
fxsdk/x/cosmos/authz/v1beta1/genesis_pb2.py
fxsdk/x/cosmos/authz/v1beta1/genesis_pb2_grpc.py
fxsdk/x/cosmos/authz/v1beta1/query_pb2.py
fxsdk/x/cosmos/authz/v1beta1/query_pb2_grpc.py
fxsdk/x/cosmos/authz/v1beta1/tx_pb2.py
fxsdk/x/cosmos/authz/v1beta1/tx_pb2_grpc.py
fxsdk/x/cosmos/bank/__init__.py
fxsdk/x/cosmos/bank/v1beta1/__init__.py
fxsdk/x/cosmos/bank/v1beta1/authz_pb2.py
fxsdk/x/cosmos/bank/v1beta1/authz_pb2_grpc.py
fx_py_sdk-0.7.3.dist-info/LICENSE
fx_py_sdk-0.7.3.dist-info/METADATA
fx_py_sdk-0.7.3.dist-info/WHEEL
fx_py_sdk-0.7.3.dist-info/top_level.txt
fx_py_sdk-0.7.3.dist-info/RECORD
