Metadata-Version: 2.1
Name: fx-py-sdk
Version: 0.7.3
Summary: Python library for FunctionX
Home-page: https://github.com/functionx/fx-py-sdk
Author: zakir
Keywords: FunctionX,blockchain
Platform: any
Classifier: Development Status :: 4 - Beta
Classifier: Intended Audience :: Developers
Classifier: License :: OSI Approved :: Apache Software License
Classifier: Programming Language :: Python :: 3
Classifier: Programming Language :: Python :: 3.7
Classifier: Programming Language :: Python :: 3.9
Classifier: Programming Language :: Python :: 3.11
Requires-Python: >=3.7
License-File: LICENSE
Requires-Dist: grpcio >=1.59.0
Requires-Dist: google-api-python-client >=2.102.0
Requires-Dist: bech32 >=1.2.0
Requires-Dist: ecdsa >=0.18.0
Requires-Dist: hdwallets >=0.1.2
Requires-Dist: mnemonic >=0.20
Requires-Dist: eth-utils >=2.2.2
Requires-Dist: coincurve >=18.0.0
Requires-Dist: pycryptodome >=3.19.0
